[{"action":"UPDATE","id":"GXB22TEu","data":{"name":"Operation Thunder","id":"GXB22TEu","manufacturer":"Gottlieb","year":1992,"MPU":"Gottlieb System 3","theme":[],"players":4,"designers":["Ray Tanzer"],"ipdbUrl":"http://www.ipdb.org/machine.cgi?id=1721","type":"SS","updatedAt":1674882000000,"tableFiles":[{"id":"Fzh9p1f7zE","createdAt":1674882000000,"updatedAt":1674951194186,"imgUrl":"https://fraesh.github.io/vps-db/img/GXB22TEu_table_1674834772559.webp","urls":[{"url":"https://vpuniverse.com/files/file/12911-operation-thunder-gottlieb-1992-108/"},{"url":"https://www.vpforums.org/index.php?s=307dc80dd0e2fc6bde1f762adbb2e982&app=downloads&showfile=17072"}],"authors":["Rascal","mfuegemann","Ahr1man","Rawd","Gigalula","tamoore"],"tableFormat":"VPX","features":["Hybrid","VR","FSS"],"version":"1.4.0"},{"urls":[{"url":"https://www.vpforums.org/index.php?app=downloads&showfile=14735","broken":false}],"theme":[],"comment":"Bigus MOD","version":"3.1","authors":["Bigus1","Mfuegemann","Rascal","Scutters"],"updatedAt":1671634866056,"createdAt":1671577200000,"tableFormat":"VPX","features":["MOD","FlexDMD"],"imgUrl":"https://fraesh.github.io/vps-db/img/18feba54bdc035887ffad11b9f18faa6_table_1638093698372.webp","id":"8t6N7Cng"},{"urls":[{"url":"https://vpuniverse.com/files/file/5476-operation-thunder-1992-gottliebpremier/"}],"theme":[],"comment":"VP9 to VPX Conversion","version":"1.1.0","authors":["Rascal","Mfuegemann","Akiles5000","Zaphod","Destruk","Scapino","Fuzzel","JPSalas","Arngrim"],"updatedAt":1656666839651,"createdAt":1550012400000,"tableFormat":"VPX","id":"guuH3VOZ","imgUrl":"https://fraesh.github.io/vps-db/img/GXB22TEu_table_1656666871618.webp"}],"b2sFiles":[{"id":"fv3HidwC6a","createdAt":1666709612681,"imgUrl":"https://fraesh.github.io/vps-db/img/GXB22TEu_b2s_1666709620051.webp","urls":[{"url":"https://vpuniverse.com/files/file/11920-operation-thunder-gottlieb-1992-b2s-with-full-dmd/"}],"comment":"b2s with full DMD","version":"1.0","updatedAt":1666709636186,"authors":["Hauntfreaks","Wildman"]},{"urls":[{"url":"https://vpuniverse.com/files/file/2549-operation-thunder-gottlieb-1992/"}],"version":"2.0","authors":["Wildman"],"updatedAt":1656666899946,"id":"qJ-4MZTQ","imgUrl":"https://fraesh.github.io/vps-db/img/GXB22TEu_b2s_1656666911558.webp"}],"povFiles":[{"version":"1.0","urls":[{"url":"http://bit.ly/POVs_RaJo","broken":false}],"authors":["Rajo Joey"],"updatedAt":1563141600000,"id":"jtuIN_Ue"}],"wheelArtFiles":[{"urls":[{"url":"https://mega.nz/#F!p3hREDgB!pEWMJvVQ7t3Sv_TmrxdU-w!52AzHIDR","broken":false}],"version":"1.0","authors":["Calium"],"updatedAt":1517439600000,"id":"TzQWpeZE"}],"mediaPackFiles":[{"urls":[{"url":"http://www.vpforums.org/index.php?app=downloads&showfile=10676","broken":false}],"version":"1.0","authors":["Stat"],"updatedAt":1423868400000,"id":"NbVVjRIF"}],"features":["Hybrid","VR","FSS","VPX","MOD","FlexDMD","B2S","POV","Wheel","MediaPack"],"lastCreatedAt":1674882000000,"broken":false}}]