[{"action":"UPDATE","id":"ZxOdqKhi","data":{"name":"Big Bang Bar","id":"ZxOdqKhi","manufacturer":"Capcom","year":1996,"MPU":"Capcom A0015405","theme":["Outer Space"],"players":4,"designers":["Rob Morrison"],"ipdbUrl":"http://www.ipdb.org/machine.cgi?id=4001","type":"SS","updatedAt":1649368800000,"tableFiles":[{"id":"EwpeBf_zfK","createdAt":1649368800000,"updatedAt":1649368539661,"tableFormat":"VPX","theme":["Outer Space"],"authors":["Gedankekojote97","Unclewilly","Bigus1","VPW Team"],"version":"1.1.1.1 1.0","features":["MOD"],"urls":[{"url":"https://vpuniverse.com/files/file/9785-big-bang-bar-mod-nfozzy-fleep-sounds-lut-1111/"}],"imgUrl":"https://fraesh.github.io/vps-db/img/ZxOdqKhi_table_1649368609685.webp","comment":"Mod"},{"urls":[{"url":"https://vpinball.com/VPBdownloads/big-bang-bar-2/","broken":true}],"theme":["Outer Space"],"comment":"MOD","version":"2.4.6","authors":["UncleWilly","ClarkKent","Ninuzzu","Flupper"],"updatedAt":1595541600000,"createdAt":1595541600000,"tableFormat":"VPX","features":["MOD"],"id":"011qsxQs"},{"urls":[{"url":"https://www.vpforums.org/index.php?app=downloads&showfile=15000","broken":false}],"theme":["Outer Space"],"comment":"Graphical Update MOD","version":"1.0","authors":["Sheltemke","UncleWilly","Bigus1","Schreibi34","Ninuzzu","JimmyFingers","Grizz","Rom"],"updatedAt":1589493600000,"createdAt":1589493600000,"tableFormat":"VPX","features":["MOD"],"imgUrl":"https://fraesh.github.io/vps-db/img/32cc3eae437380237fdeef4627664227_table_1638093698083.webp","id":"zL4Mo0At"},{"urls":[{"url":"https://www.vpforums.org/index.php?app=downloads&showfile=14734","broken":false}],"theme":["Outer Space"],"comment":"Bigus MOD","version":"1.1","authors":["Bigus1","Ninuzzu","UncleWilly","JimmyFingers","Grizz","Rom","Thalamus","Zigbane"],"updatedAt":1583362800000,"createdAt":1583362800000,"tableFormat":"VPX","features":["MOD"],"imgUrl":"https://fraesh.github.io/vps-db/img/32cc3eae437380237fdeef4627664227_table_1638093698084.webp","id":"02GK43yX"},{"urls":[{"url":"https://vpinball.com/VPBdownloads/fss-mod-big-bang-bar-capcom-1996/","broken":true}],"theme":["Outer Space"],"comment":"FSS (Full Single Screen) MOD","version":"1.0 FSS Rev. R2.5","authors":["Arconovum","Randr","UncleWilly"],"updatedAt":1542150000000,"createdAt":1542150000000,"tableFormat":"VPX","features":["FSS","MOD"],"id":"lWUCH3K-"},{"urls":[{"url":"http://vpinball.com/VPBdownloads/big-bang-bar/","broken":true}],"theme":["Outer Space"],"version":"1.0","authors":["Randr","UncleWilly","Ninuzzu"],"updatedAt":1458860400000,"createdAt":1458860400000,"tableFormat":"VPX","id":"B94zj6PB"}],"b2sFiles":[{"urls":[{"url":"http://vpuniverse.com/forums/files/file/5111-big-bang-bar-capcom-1996/","broken":false}],"version":"1.0.0","authors":["Wildman"],"updatedAt":1525125600000,"imgUrl":"https://fraesh.github.io/vps-db/img/32cc3eae437380237fdeef4627664227_b2s_1638093727992.webp","id":"1WMhfL8n"}],"romFiles":[{"version":"bbb109","urls":[{"url":"http://www.vpforums.org/index.php?app=downloads&showfile=418","broken":false}],"authors":["Destruk"],"updatedAt":1359068400000,"id":"Ks3T1Xy7"}],"povFiles":[{"version":"1.0","urls":[{"url":"http://bit.ly/POVs_RaJo","broken":false}],"authors":["Rajo Joey"],"updatedAt":1563141600000,"id":"-4_MFHzM"}],"wheelArtFiles":[{"urls":[{"url":"https://mega.nz/#F!p3hREDgB!pEWMJvVQ7t3Sv_TmrxdU-w!52AzHIDR","broken":false}],"version":"1.0","authors":["Calium"],"updatedAt":1517439600000,"id":"Z3BkGsDU"}],"mediaPackFiles":[{"urls":[{"url":"http://www.vpforums.org/index.php?app=downloads&showfile=6405","broken":false}],"version":"1.0.0","authors":["Bitupset"],"updatedAt":1332198000000,"id":"4le2-5-I"}],"soundFiles":[{"urls":[{"url":"https://www.dropbox.com/s/6rf42gb10u19qwa/Big%20Bang%20Bar%20%28Capcom%201996%29.mp3?dl=0","broken":false}],"version":"","authors":[],"updatedAt":946681200000}],"features":["MOD","VPX","FSS","B2S","ROM","POV","Wheel","MediaPack","PinX Sound"],"lastCreatedAt":1649368800000,"broken":true}},{"action":"UPDATE","id":"C14QMndG","data":{"name":"Power Play, Bobby Orr's","id":"C14QMndG","manufacturer":"Bally","year":1978,"MPU":"Bally MPU AS-2518-17","theme":["Sports","Hockey","Celebrity"],"players":4,"designers":["Greg Kmiec"],"ipdbUrl":"http://www.ipdb.org/machine.cgi?id=1858","type":"SS","updatedAt":1649368800000,"tableFiles":[{"urls":[{"url":"https://vpuniverse.com/files/file/9794-bobby-orr-power-play-bally-1977/"}],"theme":["Sports","Hockey","Celebrity"],"version":"2.1","authors":["Bord","Arngrim","TheLoafer","CyclonePF","Thalamus","Rothbauerw","UnclePaulie"],"updatedAt":1649413854988,"createdAt":1649368800000,"tableFormat":"VPX","features":["FastFlips","VR"],"id":"T3W8qNSq","comment":"Includes VR Room option","imgUrl":"https://fraesh.github.io/vps-db/img/C14QMndG_table_1649413906700.webp"},{"urls":[{"url":"https://vpinball.com/VPBdownloads/fss-mod-bobby-orrs-power-play-bally-1977/","broken":true}],"theme":["Sports","Hockey","Celebrity"],"comment":"FSS (Full Single Screen) MOD","version":"1.0 FSS Rev. R2.5","authors":["Arconovum","Bord"],"updatedAt":1542495600000,"createdAt":1542495600000,"tableFormat":"VPX","features":["FastFlips","FSS","MOD"],"id":"sUcNLoW8"}],"b2sFiles":[{"urls":[{"url":"https://vpuniverse.com/files/file/2976-power-play-bally-1977/"}],"version":"1.0","authors":["Wildman"],"updatedAt":1605394800000,"id":"hv9hLnuA","imgUrl":"https://fraesh.github.io/vps-db/img/C14QMndG_b2s_1647691007365.webp"}],"povFiles":[{"version":"1.0","urls":[{"url":"http://bit.ly/POVs_RaJo","broken":false}],"authors":["Rajo Joey"],"updatedAt":1563141600000,"id":"M1uAvVpm"}],"wheelArtFiles":[{"urls":[{"url":"http://vpinball.com/VPBdownloads/power-play-bally-1977-wheel/","broken":true}],"version":"1.0","authors":["HauntFreaks"],"updatedAt":1517698800000,"id":"fSBGcTpI"},{"urls":[{"url":"https://mega.nz/#F!p3hREDgB!pEWMJvVQ7t3Sv_TmrxdU-w!52AzHIDR","broken":false}],"version":"1.0","authors":["Calium"],"updatedAt":1517439600000,"id":"vjirLgWg"}],"mediaPackFiles":[{"urls":[{"url":"http://www.vpforums.org/index.php?app=downloads&showfile=4468","broken":false}],"version":"1.0.0","authors":["Bitupset"],"updatedAt":1290812400000,"id":"CXVal3_N"}],"features":["FastFlips","VR","VPX","FSS","MOD","B2S","POV","Wheel","MediaPack"],"lastCreatedAt":1649368800000,"broken":true}},{"action":"UPDATE","id":"5ucOcBHm","data":{"name":"Batman","id":"5ucOcBHm","manufacturer":"Data East","year":1991,"MPU":"DataEast/Sega Version 3","theme":["Celebrities","Fictional","Licensed Theme"],"players":4,"designers":["Joe Kaminkow","Ed Cebula"],"ipdbUrl":"http://www.ipdb.org/machine.cgi?id=195","type":"SS","updatedAt":1649368800000,"tableFiles":[{"id":"61CvKy0phe","createdAt":1649368800000,"updatedAt":1649198963258,"theme":["Celebrities","Fictional","Licensed Theme"],"tableFormat":"VPX","urls":[{"url":"https://vpuniverse.com/files/file/9762-batman-1989-data-east-balutito-mod/"}],"version":"1.0.0","authors":["Balutito","Javier1515"],"comment":"Balutito Mod","features":["MOD","incl. B2S"],"imgUrl":"https://fraesh.github.io/vps-db/img/5ucOcBHm_table_1649199039919.webp"},{"urls":[{"url":"https://vpuniverse.com/forums/files/file/7502-batman-data-east-1991-vpw/","broken":false}],"theme":["Celebrities","Fictional","Licensed Theme"],"comment":"VPW (VPinWorkshop) version","version":"1.1","authors":["VPinWorkshop","Cyberpez","SKitso","Iaaki","Fluffhead35","Baldgeek","Sixtoe","Apophis","Wylte","Oqqsan","Tomate"],"updatedAt":1638911155819,"createdAt":1638831600000,"tableFormat":"VPX","features":["VR"],"imgUrl":"https://fraesh.github.io/vps-db/img/b9cc368aa6b35a05ed2b6e252465b637_table_1638305103795.webp","id":"99azbvfU"},{"createdAt":1625954400000,"theme":["Celebrities","Fictional","Licensed Theme"],"updatedAt":1638305220904,"tableFormat":"VPX","urls":[{"url":"https://vpuniverse.com/forums/files/file/6977-batman-data-east-1991-sg1bson-bw-mod/"}],"version":"1.0.0","features":["MOD","incl. B2S","incl. Art"],"comment":"SG1bsoN Black and White MOD","authors":["SG1bsoN","Javier","Dark","Ben Logan","85vett","Jawdax","cyberprez","flupper1","Daniel Ivan"],"imgUrl":"https://fraesh.github.io/vps-db/img/b9cc368aa6b35a05ed2b6e252465b637_table_1638305219962.webp","id":"uML5AtcJ"},{"urls":[{"url":"https://www.vpforums.org/index.php?app=downloads&showfile=15137","broken":false}],"theme":["Celebrities","Fictional","Licensed Theme"],"comment":"Bigus MOD","version":"1.1","authors":["Bigus1","Javier1515","Dark"],"updatedAt":1604271600000,"createdAt":1604271600000,"tableFormat":"VPX","features":["MOD"],"imgUrl":"https://fraesh.github.io/vps-db/img/b9cc368aa6b35a05ed2b6e252465b637_table_1638911195915.webp","id":"eu0Pp5WO"},{"urls":[{"url":"https://vpinball.com/VPBdownloads/fss-mod-batman-data-east-1990/","broken":true}],"theme":["Celebrities","Fictional","Licensed Theme"],"comment":"FSS (Full Single Screen) MOD","version":"1.2 FSS Rev. R2.5","authors":["Arconovum","Javier1515"],"updatedAt":1542495600000,"createdAt":1542495600000,"tableFormat":"VPX","features":["FastFlips","FSS","MOD"],"id":"9DXL3Rma"},{"urls":[{"url":"http://www.vpforums.org/index.php?s=a6dee3a6cbb2b271959837cb34cc0df6&app=downloads&showfile=12757","broken":false}],"theme":["Celebrities","Fictional","Licensed Theme"],"version":"1.3","authors":["Javier","Dark","Ben Logan"],"updatedAt":1494540000000,"createdAt":1494540000000,"tableFormat":"VPX","imgUrl":"https://fraesh.github.io/vps-db/img/b9cc368aa6b35a05ed2b6e252465b637_table_1638911217875.webp","id":"6XbWUJ-R"},{"urls":[{"url":"https://tinyurl.com/ydgxax9n","broken":false}],"theme":["Celebrities","Fictional","Licensed Theme"],"comment":"Surround MOD","version":"1.3","authors":["Javier1515","RustyCardores"],"updatedAt":946681200000,"createdAt":946681200000,"tableFormat":"VPX","features":["SSF"],"id":"6TFChFSn"}],"b2sFiles":[{"id":"0tN6vcEvoI","createdAt":1649199087579,"urls":[{"url":"https://vpuniverse.com/files/file/9763-b2s-batman-data-east-balutito-mod/"}],"version":"1.0.0","updatedAt":1649199094194,"authors":["Balutito"],"imgUrl":"https://fraesh.github.io/vps-db/img/5ucOcBHm_b2s_1649199114418.webp"},{"urls":[{"url":"http://www.vpforums.org/index.php?app=downloads&showfile=7613","broken":false}],"version":"1.0","authors":["Teamtechnic"],"updatedAt":1362956400000,"imgUrl":"https://fraesh.github.io/vps-db/img/b9cc368aa6b35a05ed2b6e252465b637_b2s_1638093204879.webp","id":"ctsySg4O"}],"romFiles":[{"version":"btmn_106","urls":[{"url":"https://www.vpforums.org/index.php?app=downloads&showfile=832","broken":false}],"authors":["Destruk"],"updatedAt":1359068400000,"id":"9zD-1Nt4"}],"altColorFiles":[{"urls":[{"url":"http://vpuniverse.com/forums/files/file/5777-batman-data-east1991/","broken":false}],"version":"1.0.2","authors":["MydknyteStyrm"],"updatedAt":1601762400000,"id":"rz6wpDyd"}],"altSoundFiles":[{"urls":[{"url":"https://vpuniverse.com/forums/files/file/5939-altsound-batman-data-east-1991-ost-remastered/","broken":false}],"version":"1.0.0","authors":["iDigStuff","Baptiste"],"updatedAt":1631397600000,"id":"SulIX8ns"}],"povFiles":[{"version":"1.0","urls":[{"url":"http://bit.ly/POVs_RaJo","broken":false}],"authors":["Rajo Joey"],"updatedAt":1563141600000,"id":"wQtSN3hR"}],"pupPackFiles":[{"name":"BATMAN (Data East) PuP-Pack","version":"2.0","urls":[{"url":"https://vpinball.com/VPBdownloads/batman-data-east-pup-pack/","broken":true}],"authors":["MisterKai"],"updatedAt":1550876400000,"id":"Iauw0oI3"}],"wheelArtFiles":[{"urls":[{"url":"http://vpuniverse.com/forums/files/file/4525-front-end-wheel-images-by-laylow/","broken":false}],"version":"1.0","authors":["Laylow"],"updatedAt":1484694000000,"id":"D-WyaKCg"},{"urls":[{"url":"https://mega.nz/#F!p3hREDgB!pEWMJvVQ7t3Sv_TmrxdU-w!52AzHIDR","broken":false}],"version":"1.0","authors":["Calium"],"updatedAt":1517439600000,"id":"thFAw4Gg"}],"topperFiles":[{"urls":[{"url":"http://vpuniverse.com/forums/files/file/4749-topper-videos/","broken":false}],"version":"1.1.3","authors":["BambiPlattfuss"],"updatedAt":1498514400000,"id":"ukKFIboY"}],"mediaPackFiles":[{"urls":[{"url":"http://www.vpforums.org/index.php?app=downloads&showfile=4337","broken":false}],"version":"1.0.0","authors":["Bitupset"],"updatedAt":1290639600000,"id":"GsKaVdqi"}],"soundFiles":[{"urls":[{"url":"https://www.dropbox.com/s/iungddp07ppy03g/Batman%20%28Data%20East%201991%29.mp3?dl=0","broken":false}],"version":"","authors":[],"updatedAt":946681200000}],"features":["MOD","incl. B2S","VPX","VR","incl. Art","FastFlips","FSS","SSF","B2S","ROM","POV","Color","Sound","PuP","Wheel","MediaPack","Topper","PinX Sound"],"lastCreatedAt":1649368800000,"broken":true,"imgUrl":"https://fraesh.github.io/vps-db/img/b9cc368aa6b35a05ed2b6e252465b637_b2s_1638093204879.webp"}}]