[{"action":"UPDATE","id":"iNCMlR5mWl","data":{"name":"The Labyrinth","type":"SS","manufacturer":"Original","year":2023,"theme":["Movie","Fantasy"],"tableFiles":[{"id":"kiBIoviC9t","createdAt":1694296800000,"updatedAt":1694340860000,"tableFormat":"VPX","theme":["Movie","Fantasy"],"authors":["Jagandy82","JPSalas"],"version":"1.2","urls":[{"url":"https://vpuniverse.com/files/file/15100-the-labyrinth/"}],"features":["incl. PuP","incl. Art","incl. B2S","incl. Video"],"comment":"MOD of Skateball (Bally 1980)","imgUrl":"https://fraesh.github.io/vps-db/img/undefined_table_1689321487429.webp"}],"features":["incl. PuP","incl. Art","incl. B2S","incl. Video","VPX","B2S","ROM"],"broken":false,"updatedAt":1694296800000,"lastCreatedAt":1694296800000,"id":"iNCMlR5mWl","b2sFiles":[{"id":"th5U8-Z33_","createdAt":1689582405419,"urls":[{"url":"https://vpuniverse.com/files/file/15122-labyrinth-backglass-with-fulldmd/"}],"features":["FullDMD"],"authors":["GauGau"],"imgUrl":"https://vpuniverse.com/screenshots/monthly_2023_07/LabyrinthIlluminated.png.ce060ac7b5b5c1f73c09be0482b5edf4.png","version":"1.0.0","updatedAt":1689582439511},{"id":"pm1RFLHltf","createdAt":1694600420944,"urls":[{"url":"https://vpuniverse.com/files/file/15884-the-labyrinth-original-2023-2-3-screens-animated-backglass/"}],"authors":["Marcobus2005"],"features":["FullDMD"],"imgUrl":"https://fraesh.github.io/vps-db/img/iNCMlR5mWl_b2s_1694600485314.webp","version":"1.0.0","updatedAt":1694600491087}],"romFiles":[{"id":"Pf7rTAhmlB","createdAt":1689582719856,"updatedAt":1689582730568,"urls":[{"url":"https://www.vpforums.org/index.php?app=downloads&showfile=674"}],"version":"skatebll","authors":["Destruk"]}]}},{"action":"UPDATE","id":"ojcmHOaZ","data":{"name":"Sonic the Hedgehog","id":"ojcmHOaZ","manufacturer":"Original","year":2005,"theme":["Video Game","Kids"],"designers":[],"ipdbUrl":"Not Available","type":"SS","updatedAt":1694390400000,"tableFiles":[{"id":"TYVVL51gSe","createdAt":1694390400000,"updatedAt":1694600141062,"tableFormat":"VPX","imgUrl":"https://fraesh.github.io/vps-db/img/IZOsZDfC_table_1694599986014.webp","authors":["Panasony","DCrosby","Javier1515","Brendan Bailey (Pinwizkid)"],"version":"1.2","features":["MOD"],"comment":"Bug Fixes","urls":[{"url":"https://www.vpforums.org/index.php?app=downloads&showfile=17707"}]},{"urls":[{"url":"https://www.vpforums.org/index.php?app=downloads&showfile=14212","broken":false}],"theme":["Videogame","Kids"],"comment":"FlexDMD MOD of Sonic The Hedgehog 2 (Original 2005)","version":"1.10","authors":["DCrosby","Javier1515","Brendan Bailey (Pinwizkid)"],"updatedAt":1558562400000,"createdAt":1558562400000,"tableFormat":"VPX","features":["FlexDMD","Kids","MOD"],"imgUrl":"https://fraesh.github.io/vps-db/img/5557f81f1e81f62b5af5d562fed09faf_table_1638093698449.webp","id":"f5q3HhqW"},{"id":"vxmVY4bPId","createdAt":1391558400000,"updatedAt":1691498244625,"urls":[{"url":"https://pinballnirvana.com/forums/resources/sonic-the-hedgehog-original-ultimate.7404/"}],"authors":["SLAMT1LT","Atros","Brendan Bailey (Pinwizkid)"],"tableFormat":"FP","comment":"Ultimate Edition- Physics 2.6","version":"1.02","imgUrl":"https://fraesh.github.io/vps-db/img/ojcmHOaZ_table_1691498287582.webp","features":["MOD"]}],"features":["MOD","VPX","FlexDMD","Kids","FP","Wheel"],"lastCreatedAt":1694390400000,"broken":false,"b2sFiles":[],"imgUrl":"https://fraesh.github.io/vps-db/img/ojcmHOaZ_b2s_1691298574079.webp","wheelArtFiles":[{"id":"TchXRNnLG1","createdAt":1693313953432,"updatedAt":1693313960060,"urls":[{"url":"https://vpuniverse.com/files/file/14433-sonic-pinball-party-wheel/"}],"version":"1.0.0 (Animated)","authors":["Mitshiba"]}]}}]